MANIFEST.in
NEWS.txt
README.md
setup.py
rec_env/__init__.py
rec_env.egg-info/PKG-INFO
rec_env.egg-info/SOURCES.txt
rec_env.egg-info/dependency_links.txt
rec_env.egg-info/not-zip-safe
rec_env.egg-info/requires.txt
rec_env.egg-info/top_level.txt
tests/__init__.py
tests/test_missing_fmt.py
tests/test_rec_env.py