Metadata-Version: 1.0
Name: rec-env
Version: 0.0.4
Summary: UNKNOWN
Home-page: UNKNOWN
Author: Luiz Irber
Author-email: luiz.irber@gmail.com
License: PSF
Platform: any
